{"nodes": [{"id": "d_git_openjarvis_windows_focused_src_openjarvis_evals_tests_test_supergpqa_py", "label": "test_supergpqa.py", "file_type": "code", "source_file": "D:\\Git\\OpenJarvis-Windows-focused\\src\\openjarvis\\evals\\tests\\test_supergpqa.py", "source_location": "L1"}, {"id": "tests_test_supergpqa_testsupergpqascorer", "label": "TestSuperGPQAScorer", "file_type": "code", "source_file": "D:\\Git\\OpenJarvis-Windows-focused\\src\\openjarvis\\evals\\tests\\test_supergpqa.py", "source_location": "L9"}, {"id": "tests_test_supergpqa_testsupergpqascorer_make_record", "label": "._make_record()", "file_type": "code", "source_file": "D:\\Git\\OpenJarvis-Windows-focused\\src\\openjarvis\\evals\\tests\\test_supergpqa.py", "source_location": "L10"}, {"id": "tests_test_supergpqa_testsupergpqascorer_test_correct_extraction", "label": ".test_correct_extraction()", "file_type": "code", "source_file": "D:\\Git\\OpenJarvis-Windows-focused\\src\\openjarvis\\evals\\tests\\test_supergpqa.py", "source_location": "L27"}, {"id": "tests_test_supergpqa_testsupergpqascorer_test_incorrect_extraction", "label": ".test_incorrect_extraction()", "file_type": "code", "source_file": "D:\\Git\\OpenJarvis-Windows-focused\\src\\openjarvis\\evals\\tests\\test_supergpqa.py", "source_location": "L41"}, {"id": "tests_test_supergpqa_testsupergpqascorer_test_missing_reference", "label": ".test_missing_reference()", "file_type": "code", "source_file": "D:\\Git\\OpenJarvis-Windows-focused\\src\\openjarvis\\evals\\tests\\test_supergpqa.py", "source_location": "L54"}, {"id": "tests_test_supergpqa_testsupergpqascorer_test_no_extraction", "label": ".test_no_extraction()", "file_type": "code", "source_file": "D:\\Git\\OpenJarvis-Windows-focused\\src\\openjarvis\\evals\\tests\\test_supergpqa.py", "source_location": "L66"}, {"id": "tests_test_supergpqa_testsupergpqascorer_test_valid_letters_from_options", "label": ".test_valid_letters_from_options()", "file_type": "code", "source_file": "D:\\Git\\OpenJarvis-Windows-focused\\src\\openjarvis\\evals\\tests\\test_supergpqa.py", "source_location": "L79"}, {"id": "tests_test_supergpqa_testsupergpqascorer_test_extraction_with_verbose_response", "label": ".test_extraction_with_verbose_response()", "file_type": "code", "source_file": "D:\\Git\\OpenJarvis-Windows-focused\\src\\openjarvis\\evals\\tests\\test_supergpqa.py", "source_location": "L94"}, {"id": "tests_test_supergpqa_rationale_1", "label": "Tests for SuperGPQA scorer logic.", "file_type": "rationale", "source_file": "D:\\Git\\OpenJarvis-Windows-focused\\src\\openjarvis\\evals\\tests\\test_supergpqa.py", "source_location": "L1"}], "edges": [{"source": "d_git_openjarvis_windows_focused_src_openjarvis_evals_tests_test_supergpqa_py", "target": "openjarvis_evals_core_types", "relation": "imports_from", "context": "import", "confidence": "EXTRACTED", "source_file": "D:\\Git\\OpenJarvis-Windows-focused\\src\\openjarvis\\evals\\tests\\test_supergpqa.py", "source_location": "L5", "weight": 1.0}, {"source": "d_git_openjarvis_windows_focused_src_openjarvis_evals_tests_test_supergpqa_py", "target": "openjarvis_evals_tests_conftest", "relation": "imports_from", "context": "import", "confidence": "EXTRACTED", "source_file": "D:\\Git\\OpenJarvis-Windows-focused\\src\\openjarvis\\evals\\tests\\test_supergpqa.py", "source_location": "L6", "weight": 1.0}, {"source": "d_git_openjarvis_windows_focused_src_openjarvis_evals_tests_test_supergpqa_py", "target": "tests_test_supergpqa_testsupergpqascorer", "relation": "contains", "confidence": "EXTRACTED", "source_file": "D:\\Git\\OpenJarvis-Windows-focused\\src\\openjarvis\\evals\\tests\\test_supergpqa.py", "source_location": "L9", "weight": 1.0}, {"source": "tests_test_supergpqa_testsupergpqascorer", "target": "tests_test_supergpqa_testsupergpqascorer_make_record", "relation": "method", "confidence": "EXTRACTED", "source_file": "D:\\Git\\OpenJarvis-Windows-focused\\src\\openjarvis\\evals\\tests\\test_supergpqa.py", "source_location": "L10", "weight": 1.0}, {"source": "tests_test_supergpqa_testsupergpqascorer", "target": "tests_test_supergpqa_testsupergpqascorer_test_correct_extraction", "relation": "method", "confidence": "EXTRACTED", "source_file": "D:\\Git\\OpenJarvis-Windows-focused\\src\\openjarvis\\evals\\tests\\test_supergpqa.py", "source_location": "L27", "weight": 1.0}, {"source": "tests_test_supergpqa_testsupergpqascorer", "target": "tests_test_supergpqa_testsupergpqascorer_test_incorrect_extraction", "relation": "method", "confidence": "EXTRACTED", "source_file": "D:\\Git\\OpenJarvis-Windows-focused\\src\\openjarvis\\evals\\tests\\test_supergpqa.py", "source_location": "L41", "weight": 1.0}, {"source": "tests_test_supergpqa_testsupergpqascorer", "target": "tests_test_supergpqa_testsupergpqascorer_test_missing_reference", "relation": "method", "confidence": "EXTRACTED", "source_file": "D:\\Git\\OpenJarvis-Windows-focused\\src\\openjarvis\\evals\\tests\\test_supergpqa.py", "source_location": "L54", "weight": 1.0}, {"source": "tests_test_supergpqa_testsupergpqascorer", "target": "tests_test_supergpqa_testsupergpqascorer_test_no_extraction", "relation": "method", "confidence": "EXTRACTED", "source_file": "D:\\Git\\OpenJarvis-Windows-focused\\src\\openjarvis\\evals\\tests\\test_supergpqa.py", "source_location": "L66", "weight": 1.0}, {"source": "tests_test_supergpqa_testsupergpqascorer", "target": "tests_test_supergpqa_testsupergpqascorer_test_valid_letters_from_options", "relation": "method", "confidence": "EXTRACTED", "source_file": "D:\\Git\\OpenJarvis-Windows-focused\\src\\openjarvis\\evals\\tests\\test_supergpqa.py", "source_location": "L79", "weight": 1.0}, {"source": "tests_test_supergpqa_testsupergpqascorer", "target": "tests_test_supergpqa_testsupergpqascorer_test_extraction_with_verbose_response", "relation": "method", "confidence": "EXTRACTED", "source_file": "D:\\Git\\OpenJarvis-Windows-focused\\src\\openjarvis\\evals\\tests\\test_supergpqa.py", "source_location": "L94", "weight": 1.0}, {"source": "tests_test_supergpqa_testsupergpqascorer_test_correct_extraction", "target": "tests_test_supergpqa_testsupergpqascorer_make_record", "relation": "calls", "context": "call", "confidence": "EXTRACTED", "source_file": "D:\\Git\\OpenJarvis-Windows-focused\\src\\openjarvis\\evals\\tests\\test_supergpqa.py", "source_location": "L34", "weight": 1.0}, {"source": "tests_test_supergpqa_testsupergpqascorer_test_incorrect_extraction", "target": "tests_test_supergpqa_testsupergpqascorer_make_record", "relation": "calls", "context": "call", "confidence": "EXTRACTED", "source_file": "D:\\Git\\OpenJarvis-Windows-focused\\src\\openjarvis\\evals\\tests\\test_supergpqa.py", "source_location": "L48", "weight": 1.0}, {"source": "tests_test_supergpqa_testsupergpqascorer_test_missing_reference", "target": "tests_test_supergpqa_testsupergpqascorer_make_record", "relation": "calls", "context": "call", "confidence": "EXTRACTED", "source_file": "D:\\Git\\OpenJarvis-Windows-focused\\src\\openjarvis\\evals\\tests\\test_supergpqa.py", "source_location": "L60", "weight": 1.0}, {"source": "tests_test_supergpqa_testsupergpqascorer_test_no_extraction", "target": "tests_test_supergpqa_testsupergpqascorer_make_record", "relation": "calls", "context": "call", "confidence": "EXTRACTED", "source_file": "D:\\Git\\OpenJarvis-Windows-focused\\src\\openjarvis\\evals\\tests\\test_supergpqa.py", "source_location": "L73", "weight": 1.0}, {"source": "tests_test_supergpqa_testsupergpqascorer_test_extraction_with_verbose_response", "target": "tests_test_supergpqa_testsupergpqascorer_make_record", "relation": "calls", "context": "call", "confidence": "EXTRACTED", "source_file": "D:\\Git\\OpenJarvis-Windows-focused\\src\\openjarvis\\evals\\tests\\test_supergpqa.py", "source_location": "L101", "weight": 1.0}, {"source": "tests_test_supergpqa_rationale_1", "target": "d_git_openjarvis_windows_focused_src_openjarvis_evals_tests_test_supergpqa_py", "relation": "rationale_for", "confidence": "EXTRACTED", "source_file": "D:\\Git\\OpenJarvis-Windows-focused\\src\\openjarvis\\evals\\tests\\test_supergpqa.py", "source_location": "L1", "weight": 1.0}], "raw_calls": [{"caller_nid": "tests_test_supergpqa_testsupergpqascorer_make_record", "callee": "EvalRecord", "is_member_call": false, "source_file": "D:\\Git\\OpenJarvis-Windows-focused\\src\\openjarvis\\evals\\tests\\test_supergpqa.py", "source_location": "L13"}, {"caller_nid": "tests_test_supergpqa_testsupergpqascorer_test_correct_extraction", "callee": "MockBackend", "is_member_call": false, "source_file": "D:\\Git\\OpenJarvis-Windows-focused\\src\\openjarvis\\evals\\tests\\test_supergpqa.py", "source_location": "L30"}, {"caller_nid": "tests_test_supergpqa_testsupergpqascorer_test_correct_extraction", "callee": "SuperGPQAScorer", "is_member_call": false, "source_file": "D:\\Git\\OpenJarvis-Windows-focused\\src\\openjarvis\\evals\\tests\\test_supergpqa.py", "source_location": "L32"}, {"caller_nid": "tests_test_supergpqa_testsupergpqascorer_test_correct_extraction", "callee": "score", "is_member_call": true, "source_file": "D:\\Git\\OpenJarvis-Windows-focused\\src\\openjarvis\\evals\\tests\\test_supergpqa.py", "source_location": "L35"}, {"caller_nid": "tests_test_supergpqa_testsupergpqascorer_test_incorrect_extraction", "callee": "MockBackend", "is_member_call": false, "source_file": "D:\\Git\\OpenJarvis-Windows-focused\\src\\openjarvis\\evals\\tests\\test_supergpqa.py", "source_location": "L44"}, {"caller_nid": "tests_test_supergpqa_testsupergpqascorer_test_incorrect_extraction", "callee": "SuperGPQAScorer", "is_member_call": false, "source_file": "D:\\Git\\OpenJarvis-Windows-focused\\src\\openjarvis\\evals\\tests\\test_supergpqa.py", "source_location": "L46"}, {"caller_nid": "tests_test_supergpqa_testsupergpqascorer_test_incorrect_extraction", "callee": "score", "is_member_call": true, "source_file": "D:\\Git\\OpenJarvis-Windows-focused\\src\\openjarvis\\evals\\tests\\test_supergpqa.py", "source_location": "L49"}, {"caller_nid": "tests_test_supergpqa_testsupergpqascorer_test_missing_reference", "callee": "MockBackend", "is_member_call": false, "source_file": "D:\\Git\\OpenJarvis-Windows-focused\\src\\openjarvis\\evals\\tests\\test_supergpqa.py", "source_location": "L57"}, {"caller_nid": "tests_test_supergpqa_testsupergpqascorer_test_missing_reference", "callee": "SuperGPQAScorer", "is_member_call": false, "source_file": "D:\\Git\\OpenJarvis-Windows-focused\\src\\openjarvis\\evals\\tests\\test_supergpqa.py", "source_location": "L58"}, {"caller_nid": "tests_test_supergpqa_testsupergpqascorer_test_missing_reference", "callee": "score", "is_member_call": true, "source_file": "D:\\Git\\OpenJarvis-Windows-focused\\src\\openjarvis\\evals\\tests\\test_supergpqa.py", "source_location": "L61"}, {"caller_nid": "tests_test_supergpqa_testsupergpqascorer_test_no_extraction", "callee": "MockBackend", "is_member_call": false, "source_file": "D:\\Git\\OpenJarvis-Windows-focused\\src\\openjarvis\\evals\\tests\\test_supergpqa.py", "source_location": "L69"}, {"caller_nid": "tests_test_supergpqa_testsupergpqascorer_test_no_extraction", "callee": "SuperGPQAScorer", "is_member_call": false, "source_file": "D:\\Git\\OpenJarvis-Windows-focused\\src\\openjarvis\\evals\\tests\\test_supergpqa.py", "source_location": "L71"}, {"caller_nid": "tests_test_supergpqa_testsupergpqascorer_test_no_extraction", "callee": "score", "is_member_call": true, "source_file": "D:\\Git\\OpenJarvis-Windows-focused\\src\\openjarvis\\evals\\tests\\test_supergpqa.py", "source_location": "L74"}, {"caller_nid": "tests_test_supergpqa_testsupergpqascorer_test_valid_letters_from_options", "callee": "MockBackend", "is_member_call": false, "source_file": "D:\\Git\\OpenJarvis-Windows-focused\\src\\openjarvis\\evals\\tests\\test_supergpqa.py", "source_location": "L82"}, {"caller_nid": "tests_test_supergpqa_testsupergpqascorer_test_valid_letters_from_options", "callee": "SuperGPQAScorer", "is_member_call": false, "source_file": "D:\\Git\\OpenJarvis-Windows-focused\\src\\openjarvis\\evals\\tests\\test_supergpqa.py", "source_location": "L83"}, {"caller_nid": "tests_test_supergpqa_testsupergpqascorer_test_valid_letters_from_options", "callee": "_valid_letters_from_options", "is_member_call": true, "source_file": "D:\\Git\\OpenJarvis-Windows-focused\\src\\openjarvis\\evals\\tests\\test_supergpqa.py", "source_location": "L87"}, {"caller_nid": "tests_test_supergpqa_testsupergpqascorer_test_valid_letters_from_options", "callee": "_valid_letters_from_options", "is_member_call": true, "source_file": "D:\\Git\\OpenJarvis-Windows-focused\\src\\openjarvis\\evals\\tests\\test_supergpqa.py", "source_location": "L91"}, {"caller_nid": "tests_test_supergpqa_testsupergpqascorer_test_extraction_with_verbose_response", "callee": "MockBackend", "is_member_call": false, "source_file": "D:\\Git\\OpenJarvis-Windows-focused\\src\\openjarvis\\evals\\tests\\test_supergpqa.py", "source_location": "L97"}, {"caller_nid": "tests_test_supergpqa_testsupergpqascorer_test_extraction_with_verbose_response", "callee": "SuperGPQAScorer", "is_member_call": false, "source_file": "D:\\Git\\OpenJarvis-Windows-focused\\src\\openjarvis\\evals\\tests\\test_supergpqa.py", "source_location": "L99"}, {"caller_nid": "tests_test_supergpqa_testsupergpqascorer_test_extraction_with_verbose_response", "callee": "score", "is_member_call": true, "source_file": "D:\\Git\\OpenJarvis-Windows-focused\\src\\openjarvis\\evals\\tests\\test_supergpqa.py", "source_location": "L102"}]}