{"nodes": [{"id": "d_git_openjarvis_windows_focused_src_openjarvis_evals_comparison_table_gen_py", "label": "table_gen.py", "file_type": "code", "source_file": "D:\\Git\\OpenJarvis-Windows-focused\\src\\openjarvis\\evals\\comparison\\table_gen.py", "source_location": "L1"}, {"id": "comparison_table_gen_tablegenerror", "label": "TableGenError", "file_type": "code", "source_file": "D:\\Git\\OpenJarvis-Windows-focused\\src\\openjarvis\\evals\\comparison\\table_gen.py", "source_location": "L33"}, {"id": "exception", "label": "Exception", "file_type": "code", "source_file": "", "source_location": ""}, {"id": "comparison_table_gen_mixedcommiterror", "label": "MixedCommitError", "file_type": "code", "source_file": "D:\\Git\\OpenJarvis-Windows-focused\\src\\openjarvis\\evals\\comparison\\table_gen.py", "source_location": "L37"}, {"id": "comparison_table_gen_noresultserror", "label": "NoResultsError", "file_type": "code", "source_file": "D:\\Git\\OpenJarvis-Windows-focused\\src\\openjarvis\\evals\\comparison\\table_gen.py", "source_location": "L41"}, {"id": "comparison_table_gen_metricstats", "label": "_MetricStats", "file_type": "code", "source_file": "D:\\Git\\OpenJarvis-Windows-focused\\src\\openjarvis\\evals\\comparison\\table_gen.py", "source_location": "L45"}, {"id": "basemodel", "label": "BaseModel", "file_type": "code", "source_file": "", "source_location": ""}, {"id": "comparison_table_gen_summaryschema", "label": "_SummarySchema", "file_type": "code", "source_file": "D:\\Git\\OpenJarvis-Windows-focused\\src\\openjarvis\\evals\\comparison\\table_gen.py", "source_location": "L51"}, {"id": "comparison_table_gen_resultsframe", "label": "ResultsFrame", "file_type": "code", "source_file": "D:\\Git\\OpenJarvis-Windows-focused\\src\\openjarvis\\evals\\comparison\\table_gen.py", "source_location": "L61"}, {"id": "comparison_table_gen_load_results", "label": "load_results()", "file_type": "code", "source_file": "D:\\Git\\OpenJarvis-Windows-focused\\src\\openjarvis\\evals\\comparison\\table_gen.py", "source_location": "L68"}, {"id": "str", "label": "str", "file_type": "code", "source_file": "D:\\Git\\OpenJarvis-Windows-focused\\src\\openjarvis\\evals\\comparison\\table_gen.py", "source_location": "L68"}, {"id": "comparison_table_gen_format_cell", "label": "_format_cell()", "file_type": "code", "source_file": "D:\\Git\\OpenJarvis-Windows-focused\\src\\openjarvis\\evals\\comparison\\table_gen.py", "source_location": "L132"}, {"id": "float", "label": "float", "file_type": "code", "source_file": "D:\\Git\\OpenJarvis-Windows-focused\\src\\openjarvis\\evals\\comparison\\table_gen.py", "source_location": "L132"}, {"id": "int", "label": "int", "file_type": "code", "source_file": "D:\\Git\\OpenJarvis-Windows-focused\\src\\openjarvis\\evals\\comparison\\table_gen.py", "source_location": "L132"}, {"id": "comparison_table_gen_render_booktabs", "label": "_render_booktabs()", "file_type": "code", "source_file": "D:\\Git\\OpenJarvis-Windows-focused\\src\\openjarvis\\evals\\comparison\\table_gen.py", "source_location": "L143"}, {"id": "dataframe", "label": "DataFrame", "file_type": "code", "source_file": "D:\\Git\\OpenJarvis-Windows-focused\\src\\openjarvis\\evals\\comparison\\table_gen.py", "source_location": "L143"}, {"id": "comparison_table_gen_build_t1", "label": "_build_t1()", "file_type": "code", "source_file": "D:\\Git\\OpenJarvis-Windows-focused\\src\\openjarvis\\evals\\comparison\\table_gen.py", "source_location": "L191"}, {"id": "comparison_table_gen_build_t2", "label": "_build_t2()", "file_type": "code", "source_file": "D:\\Git\\OpenJarvis-Windows-focused\\src\\openjarvis\\evals\\comparison\\table_gen.py", "source_location": "L228"}, {"id": "comparison_table_gen_build_t3", "label": "_build_t3()", "file_type": "code", "source_file": "D:\\Git\\OpenJarvis-Windows-focused\\src\\openjarvis\\evals\\comparison\\table_gen.py", "source_location": "L254"}, {"id": "comparison_table_gen_build_t4", "label": "_build_t4()", "file_type": "code", "source_file": "D:\\Git\\OpenJarvis-Windows-focused\\src\\openjarvis\\evals\\comparison\\table_gen.py", "source_location": "L285"}, {"id": "comparison_table_gen_build_t5", "label": "_build_t5()", "file_type": "code", "source_file": "D:\\Git\\OpenJarvis-Windows-focused\\src\\openjarvis\\evals\\comparison\\table_gen.py", "source_location": "L301"}, {"id": "comparison_table_gen_build_t6", "label": "_build_t6()", "file_type": "code", "source_file": "D:\\Git\\OpenJarvis-Windows-focused\\src\\openjarvis\\evals\\comparison\\table_gen.py", "source_location": "L317"}, {"id": "comparison_table_gen_build_t7", "label": "_build_t7()", "file_type": "code", "source_file": "D:\\Git\\OpenJarvis-Windows-focused\\src\\openjarvis\\evals\\comparison\\table_gen.py", "source_location": "L339"}, {"id": "comparison_table_gen_table_gen_default_output_dir", "label": "_table_gen_default_output_dir()", "file_type": "code", "source_file": "D:\\Git\\OpenJarvis-Windows-focused\\src\\openjarvis\\evals\\comparison\\table_gen.py", "source_location": "L371"}, {"id": "path", "label": "Path", "file_type": "code", "source_file": "D:\\Git\\OpenJarvis-Windows-focused\\src\\openjarvis\\evals\\comparison\\table_gen.py", "source_location": "L371"}, {"id": "comparison_table_gen_main", "label": "main()", "file_type": "code", "source_file": "D:\\Git\\OpenJarvis-Windows-focused\\src\\openjarvis\\evals\\comparison\\table_gen.py", "source_location": "L392"}, {"id": "comparison_table_gen_rationale_1", "label": "LaTeX table generator for the framework-comparison harness.  Reads `summary.json", "file_type": "rationale", "source_file": "D:\\Git\\OpenJarvis-Windows-focused\\src\\openjarvis\\evals\\comparison\\table_gen.py", "source_location": "L1"}, {"id": "comparison_table_gen_rationale_34", "label": "Base for table-generation problems.", "file_type": "rationale", "source_file": "D:\\Git\\OpenJarvis-Windows-focused\\src\\openjarvis\\evals\\comparison\\table_gen.py", "source_location": "L34"}, {"id": "comparison_table_gen_rationale_38", "label": "Raised when one (framework, model, benchmark) cell has multiple commits.", "file_type": "rationale", "source_file": "D:\\Git\\OpenJarvis-Windows-focused\\src\\openjarvis\\evals\\comparison\\table_gen.py", "source_location": "L38"}, {"id": "comparison_table_gen_rationale_42", "label": "Raised when no valid summary files were loaded.", "file_type": "rationale", "source_file": "D:\\Git\\OpenJarvis-Windows-focused\\src\\openjarvis\\evals\\comparison\\table_gen.py", "source_location": "L42"}, {"id": "comparison_table_gen_rationale_62", "label": "Long-format DataFrame of all loaded summary.json results.", "file_type": "rationale", "source_file": "D:\\Git\\OpenJarvis-Windows-focused\\src\\openjarvis\\evals\\comparison\\table_gen.py", "source_location": "L62"}, {"id": "comparison_table_gen_rationale_69", "label": "Glob summary.json files, validate, return long-format ResultsFrame.", "file_type": "rationale", "source_file": "D:\\Git\\OpenJarvis-Windows-focused\\src\\openjarvis\\evals\\comparison\\table_gen.py", "source_location": "L69"}, {"id": "comparison_table_gen_rationale_133", "label": "Format a single numeric cell; em-dash for missing values.", "file_type": "rationale", "source_file": "D:\\Git\\OpenJarvis-Windows-focused\\src\\openjarvis\\evals\\comparison\\table_gen.py", "source_location": "L133"}, {"id": "comparison_table_gen_rationale_150", "label": "Render a polars DataFrame as a (fragment, standalone) LaTeX tuple.      The firs", "file_type": "rationale", "source_file": "D:\\Git\\OpenJarvis-Windows-focused\\src\\openjarvis\\evals\\comparison\\table_gen.py", "source_location": "L150"}, {"id": "comparison_table_gen_rationale_192", "label": "T1: Portability triangulation.      Rows: 4 frameworks (in T1_FRAMEWORKS_ORDER).", "file_type": "rationale", "source_file": "D:\\Git\\OpenJarvis-Windows-focused\\src\\openjarvis\\evals\\comparison\\table_gen.py", "source_location": "L192"}, {"id": "comparison_table_gen_rationale_229", "label": "T2: Master efficiency comparison (mean across all benchmarks).", "file_type": "rationale", "source_file": "D:\\Git\\OpenJarvis-Windows-focused\\src\\openjarvis\\evals\\comparison\\table_gen.py", "source_location": "L229"}, {"id": "comparison_table_gen_rationale_255", "label": "T3: Per-benchmark efficiency (one detail panel \u2014 pick PinchBench).", "file_type": "rationale", "source_file": "D:\\Git\\OpenJarvis-Windows-focused\\src\\openjarvis\\evals\\comparison\\table_gen.py", "source_location": "L255"}, {"id": "comparison_table_gen_rationale_286", "label": "T4: 4-framework x all-model accuracy matrix (avg across benchmarks).", "file_type": "rationale", "source_file": "D:\\Git\\OpenJarvis-Windows-focused\\src\\openjarvis\\evals\\comparison\\table_gen.py", "source_location": "L286"}, {"id": "comparison_table_gen_rationale_302", "label": "T5: Hardware x framework efficiency (placeholder until per-hw data lands).", "file_type": "rationale", "source_file": "D:\\Git\\OpenJarvis-Windows-focused\\src\\openjarvis\\evals\\comparison\\table_gen.py", "source_location": "L302"}, {"id": "comparison_table_gen_rationale_318", "label": "T6: Token economy decomposition (preliminary; total in/out only).      Spec \u00a76.3", "file_type": "rationale", "source_file": "D:\\Git\\OpenJarvis-Windows-focused\\src\\openjarvis\\evals\\comparison\\table_gen.py", "source_location": "L318"}, {"id": "comparison_table_gen_rationale_340", "label": "T7: Edit category x framework \u2014 preliminary (raw deltas).      Spec \u00a710 says ric", "file_type": "rationale", "source_file": "D:\\Git\\OpenJarvis-Windows-focused\\src\\openjarvis\\evals\\comparison\\table_gen.py", "source_location": "L340"}, {"id": "comparison_table_gen_rationale_393", "label": "Build LaTeX tables from framework-comparison evaluation results.", "file_type": "rationale", "source_file": "D:\\Git\\OpenJarvis-Windows-focused\\src\\openjarvis\\evals\\comparison\\table_gen.py", "source_location": "L393"}], "edges": [{"source": "d_git_openjarvis_windows_focused_src_openjarvis_evals_comparison_table_gen_py", "target": "glob", "relation": "imports", "context": "import", "confidence": "EXTRACTED", "source_file": "D:\\Git\\OpenJarvis-Windows-focused\\src\\openjarvis\\evals\\comparison\\table_gen.py", "source_location": "L11", "weight": 1.0}, {"source": "d_git_openjarvis_windows_focused_src_openjarvis_evals_comparison_table_gen_py", "target": "json", "relation": "imports", "context": "import", "confidence": "EXTRACTED", "source_file": "D:\\Git\\OpenJarvis-Windows-focused\\src\\openjarvis\\evals\\comparison\\table_gen.py", "source_location": "L12", "weight": 1.0}, {"source": "d_git_openjarvis_windows_focused_src_openjarvis_evals_comparison_table_gen_py", "target": "logging", "relation": "imports", "context": "import", "confidence": "EXTRACTED", "source_file": "D:\\Git\\OpenJarvis-Windows-focused\\src\\openjarvis\\evals\\comparison\\table_gen.py", "source_location": "L13", "weight": 1.0}, {"source": "d_git_openjarvis_windows_focused_src_openjarvis_evals_comparison_table_gen_py", "target": "dataclasses", "relation": "imports_from", "context": "import", "confidence": "EXTRACTED", "source_file": "D:\\Git\\OpenJarvis-Windows-focused\\src\\openjarvis\\evals\\comparison\\table_gen.py", "source_location": "L14", "weight": 1.0}, {"source": "d_git_openjarvis_windows_focused_src_openjarvis_evals_comparison_table_gen_py", "target": "pathlib", "relation": "imports_from", "context": "import", "confidence": "EXTRACTED", "source_file": "D:\\Git\\OpenJarvis-Windows-focused\\src\\openjarvis\\evals\\comparison\\table_gen.py", "source_location": "L15", "weight": 1.0}, {"source": "d_git_openjarvis_windows_focused_src_openjarvis_evals_comparison_table_gen_py", "target": "typing", "relation": "imports_from", "context": "import", "confidence": "EXTRACTED", "source_file": "D:\\Git\\OpenJarvis-Windows-focused\\src\\openjarvis\\evals\\comparison\\table_gen.py", "source_location": "L16", "weight": 1.0}, {"source": "d_git_openjarvis_windows_focused_src_openjarvis_evals_comparison_table_gen_py", "target": "click", "relation": "imports", "context": "import", "confidence": "EXTRACTED", "source_file": "D:\\Git\\OpenJarvis-Windows-focused\\src\\openjarvis\\evals\\comparison\\table_gen.py", "source_location": "L18", "weight": 1.0}, {"source": "d_git_openjarvis_windows_focused_src_openjarvis_evals_comparison_table_gen_py", "target": "polars", "relation": "imports", "context": "import", "confidence": "EXTRACTED", "source_file": "D:\\Git\\OpenJarvis-Windows-focused\\src\\openjarvis\\evals\\comparison\\table_gen.py", "source_location": "L21", "weight": 1.0}, {"source": "d_git_openjarvis_windows_focused_src_openjarvis_evals_comparison_table_gen_py", "target": "pydantic", "relation": "imports_from", "context": "import", "confidence": "EXTRACTED", "source_file": "D:\\Git\\OpenJarvis-Windows-focused\\src\\openjarvis\\evals\\comparison\\table_gen.py", "source_location": "L28", "weight": 1.0}, {"source": "d_git_openjarvis_windows_focused_src_openjarvis_evals_comparison_table_gen_py", "target": "comparison_table_gen_tablegenerror", "relation": "contains", "confidence": "EXTRACTED", "source_file": "D:\\Git\\OpenJarvis-Windows-focused\\src\\openjarvis\\evals\\comparison\\table_gen.py", "source_location": "L33", "weight": 1.0}, {"source": "comparison_table_gen_tablegenerror", "target": "exception", "relation": "inherits", "confidence": "EXTRACTED", "source_file": "D:\\Git\\OpenJarvis-Windows-focused\\src\\openjarvis\\evals\\comparison\\table_gen.py", "source_location": "L33", "weight": 1.0}, {"source": "d_git_openjarvis_windows_focused_src_openjarvis_evals_comparison_table_gen_py", "target": "comparison_table_gen_mixedcommiterror", "relation": "contains", "confidence": "EXTRACTED", "source_file": "D:\\Git\\OpenJarvis-Windows-focused\\src\\openjarvis\\evals\\comparison\\table_gen.py", "source_location": "L37", "weight": 1.0}, {"source": "comparison_table_gen_mixedcommiterror", "target": "comparison_table_gen_tablegenerror", "relation": "inherits", "confidence": "EXTRACTED", "source_file": "D:\\Git\\OpenJarvis-Windows-focused\\src\\openjarvis\\evals\\comparison\\table_gen.py", "source_location": "L37", "weight": 1.0}, {"source": "d_git_openjarvis_windows_focused_src_openjarvis_evals_comparison_table_gen_py", "target": "comparison_table_gen_noresultserror", "relation": "contains", "confidence": "EXTRACTED", "source_file": "D:\\Git\\OpenJarvis-Windows-focused\\src\\openjarvis\\evals\\comparison\\table_gen.py", "source_location": "L41", "weight": 1.0}, {"source": "comparison_table_gen_noresultserror", "target": "comparison_table_gen_tablegenerror", "relation": "inherits", "confidence": "EXTRACTED", "source_file": "D:\\Git\\OpenJarvis-Windows-focused\\src\\openjarvis\\evals\\comparison\\table_gen.py", "source_location": "L41", "weight": 1.0}, {"source": "d_git_openjarvis_windows_focused_src_openjarvis_evals_comparison_table_gen_py", "target": "comparison_table_gen_metricstats", "relation": "contains", "confidence": "EXTRACTED", "source_file": "D:\\Git\\OpenJarvis-Windows-focused\\src\\openjarvis\\evals\\comparison\\table_gen.py", "source_location": "L45", "weight": 1.0}, {"source": "comparison_table_gen_metricstats", "target": "basemodel", "relation": "inherits", "confidence": "EXTRACTED", "source_file": "D:\\Git\\OpenJarvis-Windows-focused\\src\\openjarvis\\evals\\comparison\\table_gen.py", "source_location": "L45", "weight": 1.0}, {"source": "d_git_openjarvis_windows_focused_src_openjarvis_evals_comparison_table_gen_py", "target": "comparison_table_gen_summaryschema", "relation": "contains", "confidence": "EXTRACTED", "source_file": "D:\\Git\\OpenJarvis-Windows-focused\\src\\openjarvis\\evals\\comparison\\table_gen.py", "source_location": "L51", "weight": 1.0}, {"source": "comparison_table_gen_summaryschema", "target": "basemodel", "relation": "inherits", "confidence": "EXTRACTED", "source_file": "D:\\Git\\OpenJarvis-Windows-focused\\src\\openjarvis\\evals\\comparison\\table_gen.py", "source_location": "L51", "weight": 1.0}, {"source": "d_git_openjarvis_windows_focused_src_openjarvis_evals_comparison_table_gen_py", "target": "comparison_table_gen_resultsframe", "relation": "contains", "confidence": "EXTRACTED", "source_file": "D:\\Git\\OpenJarvis-Windows-focused\\src\\openjarvis\\evals\\comparison\\table_gen.py", "source_location": "L61", "weight": 1.0}, {"source": "d_git_openjarvis_windows_focused_src_openjarvis_evals_comparison_table_gen_py", "target": "comparison_table_gen_load_results", "relation": "contains", "confidence": "EXTRACTED", "source_file": "D:\\Git\\OpenJarvis-Windows-focused\\src\\openjarvis\\evals\\comparison\\table_gen.py", "source_location": "L68", "weight": 1.0}, {"source": "comparison_table_gen_load_results", "target": "str", "relation": "references", "context": "parameter_type", "confidence": "EXTRACTED", "source_file": "D:\\Git\\OpenJarvis-Windows-focused\\src\\openjarvis\\evals\\comparison\\table_gen.py", "source_location": "L68", "weight": 1.0}, {"source": "comparison_table_gen_load_results", "target": "comparison_table_gen_resultsframe", "relation": "references", "context": "return_type", "confidence": "EXTRACTED", "source_file": "D:\\Git\\OpenJarvis-Windows-focused\\src\\openjarvis\\evals\\comparison\\table_gen.py", "source_location": "L68", "weight": 1.0}, {"source": "d_git_openjarvis_windows_focused_src_openjarvis_evals_comparison_table_gen_py", "target": "comparison_table_gen_format_cell", "relation": "contains", "confidence": "EXTRACTED", "source_file": "D:\\Git\\OpenJarvis-Windows-focused\\src\\openjarvis\\evals\\comparison\\table_gen.py", "source_location": "L132", "weight": 1.0}, {"source": "comparison_table_gen_format_cell", "target": "float", "relation": "references", "context": "generic_arg", "confidence": "EXTRACTED", "source_file": "D:\\Git\\OpenJarvis-Windows-focused\\src\\openjarvis\\evals\\comparison\\table_gen.py", "source_location": "L132", "weight": 1.0}, {"source": "comparison_table_gen_format_cell", "target": "int", "relation": "references", "context": "parameter_type", "confidence": "EXTRACTED", "source_file": "D:\\Git\\OpenJarvis-Windows-focused\\src\\openjarvis\\evals\\comparison\\table_gen.py", "source_location": "L132", "weight": 1.0}, {"source": "comparison_table_gen_format_cell", "target": "str", "relation": "references", "context": "return_type", "confidence": "EXTRACTED", "source_file": "D:\\Git\\OpenJarvis-Windows-focused\\src\\openjarvis\\evals\\comparison\\table_gen.py", "source_location": "L132", "weight": 1.0}, {"source": "d_git_openjarvis_windows_focused_src_openjarvis_evals_comparison_table_gen_py", "target": "comparison_table_gen_render_booktabs", "relation": "contains", "confidence": "EXTRACTED", "source_file": "D:\\Git\\OpenJarvis-Windows-focused\\src\\openjarvis\\evals\\comparison\\table_gen.py", "source_location": "L143", "weight": 1.0}, {"source": "comparison_table_gen_render_booktabs", "target": "dataframe", "relation": "references", "context": "parameter_type", "confidence": "EXTRACTED", "source_file": "D:\\Git\\OpenJarvis-Windows-focused\\src\\openjarvis\\evals\\comparison\\table_gen.py", "source_location": "L143", "weight": 1.0}, {"source": "comparison_table_gen_render_booktabs", "target": "str", "relation": "references", "context": "parameter_type", "confidence": "EXTRACTED", "source_file": "D:\\Git\\OpenJarvis-Windows-focused\\src\\openjarvis\\evals\\comparison\\table_gen.py", "source_location": "L143", "weight": 1.0}, {"source": "comparison_table_gen_render_booktabs", "target": "str", "relation": "references", "context": "parameter_type", "confidence": "EXTRACTED", "source_file": "D:\\Git\\OpenJarvis-Windows-focused\\src\\openjarvis\\evals\\comparison\\table_gen.py", "source_location": "L143", "weight": 1.0}, {"source": "comparison_table_gen_render_booktabs", "target": "str", "relation": "references", "context": "parameter_type", "confidence": "EXTRACTED", "source_file": "D:\\Git\\OpenJarvis-Windows-focused\\src\\openjarvis\\evals\\comparison\\table_gen.py", "source_location": "L143", "weight": 1.0}, {"source": "comparison_table_gen_render_booktabs", "target": "int", "relation": "references", "context": "parameter_type", "confidence": "EXTRACTED", "source_file": "D:\\Git\\OpenJarvis-Windows-focused\\src\\openjarvis\\evals\\comparison\\table_gen.py", "source_location": "L143", "weight": 1.0}, {"source": "comparison_table_gen_render_booktabs", "target": "str", "relation": "references", "context": "generic_arg", "confidence": "EXTRACTED", "source_file": "D:\\Git\\OpenJarvis-Windows-focused\\src\\openjarvis\\evals\\comparison\\table_gen.py", "source_location": "L143", "weight": 1.0}, {"source": "comparison_table_gen_render_booktabs", "target": "str", "relation": "references", "context": "generic_arg", "confidence": "EXTRACTED", "source_file": "D:\\Git\\OpenJarvis-Windows-focused\\src\\openjarvis\\evals\\comparison\\table_gen.py", "source_location": "L143", "weight": 1.0}, {"source": "d_git_openjarvis_windows_focused_src_openjarvis_evals_comparison_table_gen_py", "target": "comparison_table_gen_build_t1", "relation": "contains", "confidence": "EXTRACTED", "source_file": "D:\\Git\\OpenJarvis-Windows-focused\\src\\openjarvis\\evals\\comparison\\table_gen.py", "source_location": "L191", "weight": 1.0}, {"source": "comparison_table_gen_build_t1", "target": "comparison_table_gen_resultsframe", "relation": "references", "context": "parameter_type", "confidence": "EXTRACTED", "source_file": "D:\\Git\\OpenJarvis-Windows-focused\\src\\openjarvis\\evals\\comparison\\table_gen.py", "source_location": "L191", "weight": 1.0}, {"source": "comparison_table_gen_build_t1", "target": "str", "relation": "references", "context": "generic_arg", "confidence": "EXTRACTED", "source_file": "D:\\Git\\OpenJarvis-Windows-focused\\src\\openjarvis\\evals\\comparison\\table_gen.py", "source_location": "L191", "weight": 1.0}, {"source": "comparison_table_gen_build_t1", "target": "str", "relation": "references", "context": "generic_arg", "confidence": "EXTRACTED", "source_file": "D:\\Git\\OpenJarvis-Windows-focused\\src\\openjarvis\\evals\\comparison\\table_gen.py", "source_location": "L191", "weight": 1.0}, {"source": "d_git_openjarvis_windows_focused_src_openjarvis_evals_comparison_table_gen_py", "target": "comparison_table_gen_build_t2", "relation": "contains", "confidence": "EXTRACTED", "source_file": "D:\\Git\\OpenJarvis-Windows-focused\\src\\openjarvis\\evals\\comparison\\table_gen.py", "source_location": "L228", "weight": 1.0}, {"source": "comparison_table_gen_build_t2", "target": "comparison_table_gen_resultsframe", "relation": "references", "context": "parameter_type", "confidence": "EXTRACTED", "source_file": "D:\\Git\\OpenJarvis-Windows-focused\\src\\openjarvis\\evals\\comparison\\table_gen.py", "source_location": "L228", "weight": 1.0}, {"source": "comparison_table_gen_build_t2", "target": "str", "relation": "references", "context": "generic_arg", "confidence": "EXTRACTED", "source_file": "D:\\Git\\OpenJarvis-Windows-focused\\src\\openjarvis\\evals\\comparison\\table_gen.py", "source_location": "L228", "weight": 1.0}, {"source": "comparison_table_gen_build_t2", "target": "str", "relation": "references", "context": "generic_arg", "confidence": "EXTRACTED", "source_file": "D:\\Git\\OpenJarvis-Windows-focused\\src\\openjarvis\\evals\\comparison\\table_gen.py", "source_location": "L228", "weight": 1.0}, {"source": "d_git_openjarvis_windows_focused_src_openjarvis_evals_comparison_table_gen_py", "target": "comparison_table_gen_build_t3", "relation": "contains", "confidence": "EXTRACTED", "source_file": "D:\\Git\\OpenJarvis-Windows-focused\\src\\openjarvis\\evals\\comparison\\table_gen.py", "source_location": "L254", "weight": 1.0}, {"source": "comparison_table_gen_build_t3", "target": "comparison_table_gen_resultsframe", "relation": "references", "context": "parameter_type", "confidence": "EXTRACTED", "source_file": "D:\\Git\\OpenJarvis-Windows-focused\\src\\openjarvis\\evals\\comparison\\table_gen.py", "source_location": "L254", "weight": 1.0}, {"source": "comparison_table_gen_build_t3", "target": "str", "relation": "references", "context": "generic_arg", "confidence": "EXTRACTED", "source_file": "D:\\Git\\OpenJarvis-Windows-focused\\src\\openjarvis\\evals\\comparison\\table_gen.py", "source_location": "L254", "weight": 1.0}, {"source": "comparison_table_gen_build_t3", "target": "str", "relation": "references", "context": "generic_arg", "confidence": "EXTRACTED", "source_file": "D:\\Git\\OpenJarvis-Windows-focused\\src\\openjarvis\\evals\\comparison\\table_gen.py", "source_location": "L254", "weight": 1.0}, {"source": "d_git_openjarvis_windows_focused_src_openjarvis_evals_comparison_table_gen_py", "target": "comparison_table_gen_build_t4", "relation": "contains", "confidence": "EXTRACTED", "source_file": "D:\\Git\\OpenJarvis-Windows-focused\\src\\openjarvis\\evals\\comparison\\table_gen.py", "source_location": "L285", "weight": 1.0}, {"source": "comparison_table_gen_build_t4", "target": "comparison_table_gen_resultsframe", "relation": "references", "context": "parameter_type", "confidence": "EXTRACTED", "source_file": "D:\\Git\\OpenJarvis-Windows-focused\\src\\openjarvis\\evals\\comparison\\table_gen.py", "source_location": "L285", "weight": 1.0}, {"source": "comparison_table_gen_build_t4", "target": "str", "relation": "references", "context": "generic_arg", "confidence": "EXTRACTED", "source_file": "D:\\Git\\OpenJarvis-Windows-focused\\src\\openjarvis\\evals\\comparison\\table_gen.py", "source_location": "L285", "weight": 1.0}, {"source": "comparison_table_gen_build_t4", "target": "str", "relation": "references", "context": "generic_arg", "confidence": "EXTRACTED", "source_file": "D:\\Git\\OpenJarvis-Windows-focused\\src\\openjarvis\\evals\\comparison\\table_gen.py", "source_location": "L285", "weight": 1.0}, {"source": "d_git_openjarvis_windows_focused_src_openjarvis_evals_comparison_table_gen_py", "target": "comparison_table_gen_build_t5", "relation": "contains", "confidence": "EXTRACTED", "source_file": "D:\\Git\\OpenJarvis-Windows-focused\\src\\openjarvis\\evals\\comparison\\table_gen.py", "source_location": "L301", "weight": 1.0}, {"source": "comparison_table_gen_build_t5", "target": "comparison_table_gen_resultsframe", "relation": "references", "context": "parameter_type", "confidence": "EXTRACTED", "source_file": "D:\\Git\\OpenJarvis-Windows-focused\\src\\openjarvis\\evals\\comparison\\table_gen.py", "source_location": "L301", "weight": 1.0}, {"source": "comparison_table_gen_build_t5", "target": "str", "relation": "references", "context": "generic_arg", "confidence": "EXTRACTED", "source_file": "D:\\Git\\OpenJarvis-Windows-focused\\src\\openjarvis\\evals\\comparison\\table_gen.py", "source_location": "L301", "weight": 1.0}, {"source": "comparison_table_gen_build_t5", "target": "str", "relation": "references", "context": "generic_arg", "confidence": "EXTRACTED", "source_file": "D:\\Git\\OpenJarvis-Windows-focused\\src\\openjarvis\\evals\\comparison\\table_gen.py", "source_location": "L301", "weight": 1.0}, {"source": "d_git_openjarvis_windows_focused_src_openjarvis_evals_comparison_table_gen_py", "target": "comparison_table_gen_build_t6", "relation": "contains", "confidence": "EXTRACTED", "source_file": "D:\\Git\\OpenJarvis-Windows-focused\\src\\openjarvis\\evals\\comparison\\table_gen.py", "source_location": "L317", "weight": 1.0}, {"source": "comparison_table_gen_build_t6", "target": "comparison_table_gen_resultsframe", "relation": "references", "context": "parameter_type", "confidence": "EXTRACTED", "source_file": "D:\\Git\\OpenJarvis-Windows-focused\\src\\openjarvis\\evals\\comparison\\table_gen.py", "source_location": "L317", "weight": 1.0}, {"source": "comparison_table_gen_build_t6", "target": "str", "relation": "references", "context": "generic_arg", "confidence": "EXTRACTED", "source_file": "D:\\Git\\OpenJarvis-Windows-focused\\src\\openjarvis\\evals\\comparison\\table_gen.py", "source_location": "L317", "weight": 1.0}, {"source": "comparison_table_gen_build_t6", "target": "str", "relation": "references", "context": "generic_arg", "confidence": "EXTRACTED", "source_file": "D:\\Git\\OpenJarvis-Windows-focused\\src\\openjarvis\\evals\\comparison\\table_gen.py", "source_location": "L317", "weight": 1.0}, {"source": "d_git_openjarvis_windows_focused_src_openjarvis_evals_comparison_table_gen_py", "target": "comparison_table_gen_build_t7", "relation": "contains", "confidence": "EXTRACTED", "source_file": "D:\\Git\\OpenJarvis-Windows-focused\\src\\openjarvis\\evals\\comparison\\table_gen.py", "source_location": "L339", "weight": 1.0}, {"source": "comparison_table_gen_build_t7", "target": "comparison_table_gen_resultsframe", "relation": "references", "context": "parameter_type", "confidence": "EXTRACTED", "source_file": "D:\\Git\\OpenJarvis-Windows-focused\\src\\openjarvis\\evals\\comparison\\table_gen.py", "source_location": "L339", "weight": 1.0}, {"source": "comparison_table_gen_build_t7", "target": "str", "relation": "references", "context": "generic_arg", "confidence": "EXTRACTED", "source_file": "D:\\Git\\OpenJarvis-Windows-focused\\src\\openjarvis\\evals\\comparison\\table_gen.py", "source_location": "L339", "weight": 1.0}, {"source": "comparison_table_gen_build_t7", "target": "str", "relation": "references", "context": "generic_arg", "confidence": "EXTRACTED", "source_file": "D:\\Git\\OpenJarvis-Windows-focused\\src\\openjarvis\\evals\\comparison\\table_gen.py", "source_location": "L339", "weight": 1.0}, {"source": "d_git_openjarvis_windows_focused_src_openjarvis_evals_comparison_table_gen_py", "target": "comparison_table_gen_table_gen_default_output_dir", "relation": "contains", "confidence": "EXTRACTED", "source_file": "D:\\Git\\OpenJarvis-Windows-focused\\src\\openjarvis\\evals\\comparison\\table_gen.py", "source_location": "L371", "weight": 1.0}, {"source": "comparison_table_gen_table_gen_default_output_dir", "target": "path", "relation": "references", "context": "return_type", "confidence": "EXTRACTED", "source_file": "D:\\Git\\OpenJarvis-Windows-focused\\src\\openjarvis\\evals\\comparison\\table_gen.py", "source_location": "L371", "weight": 1.0}, {"source": "d_git_openjarvis_windows_focused_src_openjarvis_evals_comparison_table_gen_py", "target": "comparison_table_gen_main", "relation": "contains", "confidence": "EXTRACTED", "source_file": "D:\\Git\\OpenJarvis-Windows-focused\\src\\openjarvis\\evals\\comparison\\table_gen.py", "source_location": "L392", "weight": 1.0}, {"source": "comparison_table_gen_main", "target": "str", "relation": "references", "context": "parameter_type", "confidence": "EXTRACTED", "source_file": "D:\\Git\\OpenJarvis-Windows-focused\\src\\openjarvis\\evals\\comparison\\table_gen.py", "source_location": "L392", "weight": 1.0}, {"source": "comparison_table_gen_main", "target": "str", "relation": "references", "context": "parameter_type", "confidence": "EXTRACTED", "source_file": "D:\\Git\\OpenJarvis-Windows-focused\\src\\openjarvis\\evals\\comparison\\table_gen.py", "source_location": "L392", "weight": 1.0}, {"source": "comparison_table_gen_main", "target": "path", "relation": "references", "context": "generic_arg", "confidence": "EXTRACTED", "source_file": "D:\\Git\\OpenJarvis-Windows-focused\\src\\openjarvis\\evals\\comparison\\table_gen.py", "source_location": "L392", "weight": 1.0}, {"source": "comparison_table_gen_load_results", "target": "path", "relation": "calls", "context": "call", "confidence": "EXTRACTED", "source_file": "D:\\Git\\OpenJarvis-Windows-focused\\src\\openjarvis\\evals\\comparison\\table_gen.py", "source_location": "L76", "weight": 1.0}, {"source": "comparison_table_gen_load_results", "target": "dataframe", "relation": "calls", "context": "call", "confidence": "EXTRACTED", "source_file": "D:\\Git\\OpenJarvis-Windows-focused\\src\\openjarvis\\evals\\comparison\\table_gen.py", "source_location": "L98", "weight": 1.0}, {"source": "comparison_table_gen_load_results", "target": "comparison_table_gen_mixedcommiterror", "relation": "calls", "context": "call", "confidence": "EXTRACTED", "source_file": "D:\\Git\\OpenJarvis-Windows-focused\\src\\openjarvis\\evals\\comparison\\table_gen.py", "source_location": "L124", "weight": 1.0}, {"source": "comparison_table_gen_load_results", "target": "comparison_table_gen_resultsframe", "relation": "calls", "context": "call", "confidence": "EXTRACTED", "source_file": "D:\\Git\\OpenJarvis-Windows-focused\\src\\openjarvis\\evals\\comparison\\table_gen.py", "source_location": "L129", "weight": 1.0}, {"source": "comparison_table_gen_render_booktabs", "target": "comparison_table_gen_format_cell", "relation": "calls", "context": "call", "confidence": "EXTRACTED", "source_file": "D:\\Git\\OpenJarvis-Windows-focused\\src\\openjarvis\\evals\\comparison\\table_gen.py", "source_location": "L167", "weight": 1.0}, {"source": "comparison_table_gen_build_t1", "target": "comparison_table_gen_render_booktabs", "relation": "calls", "context": "call", "confidence": "EXTRACTED", "source_file": "D:\\Git\\OpenJarvis-Windows-focused\\src\\openjarvis\\evals\\comparison\\table_gen.py", "source_location": "L209", "weight": 1.0}, {"source": "comparison_table_gen_build_t2", "target": "comparison_table_gen_render_booktabs", "relation": "calls", "context": "call", "confidence": "EXTRACTED", "source_file": "D:\\Git\\OpenJarvis-Windows-focused\\src\\openjarvis\\evals\\comparison\\table_gen.py", "source_location": "L245", "weight": 1.0}, {"source": "comparison_table_gen_build_t3", "target": "comparison_table_gen_render_booktabs", "relation": "calls", "context": "call", "confidence": "EXTRACTED", "source_file": "D:\\Git\\OpenJarvis-Windows-focused\\src\\openjarvis\\evals\\comparison\\table_gen.py", "source_location": "L277", "weight": 1.0}, {"source": "comparison_table_gen_build_t4", "target": "comparison_table_gen_render_booktabs", "relation": "calls", "context": "call", "confidence": "EXTRACTED", "source_file": "D:\\Git\\OpenJarvis-Windows-focused\\src\\openjarvis\\evals\\comparison\\table_gen.py", "source_location": "L293", "weight": 1.0}, {"source": "comparison_table_gen_build_t5", "target": "comparison_table_gen_render_booktabs", "relation": "calls", "context": "call", "confidence": "EXTRACTED", "source_file": "D:\\Git\\OpenJarvis-Windows-focused\\src\\openjarvis\\evals\\comparison\\table_gen.py", "source_location": "L308", "weight": 1.0}, {"source": "comparison_table_gen_build_t5", "target": "dataframe", "relation": "calls", "context": "call", "confidence": "EXTRACTED", "source_file": "D:\\Git\\OpenJarvis-Windows-focused\\src\\openjarvis\\evals\\comparison\\table_gen.py", "source_location": "L309", "weight": 1.0}, {"source": "comparison_table_gen_build_t5", "target": "comparison_table_gen_build_t2", "relation": "calls", "context": "call", "confidence": "EXTRACTED", "source_file": "D:\\Git\\OpenJarvis-Windows-focused\\src\\openjarvis\\evals\\comparison\\table_gen.py", "source_location": "L314", "weight": 1.0}, {"source": "comparison_table_gen_build_t6", "target": "comparison_table_gen_render_booktabs", "relation": "calls", "context": "call", "confidence": "EXTRACTED", "source_file": "D:\\Git\\OpenJarvis-Windows-focused\\src\\openjarvis\\evals\\comparison\\table_gen.py", "source_location": "L331", "weight": 1.0}, {"source": "comparison_table_gen_build_t7", "target": "comparison_table_gen_render_booktabs", "relation": "calls", "context": "call", "confidence": "EXTRACTED", "source_file": "D:\\Git\\OpenJarvis-Windows-focused\\src\\openjarvis\\evals\\comparison\\table_gen.py", "source_location": "L352", "weight": 1.0}, {"source": "comparison_table_gen_table_gen_default_output_dir", "target": "path", "relation": "calls", "context": "call", "confidence": "EXTRACTED", "source_file": "D:\\Git\\OpenJarvis-Windows-focused\\src\\openjarvis\\evals\\comparison\\table_gen.py", "source_location": "L372", "weight": 1.0}, {"source": "comparison_table_gen_main", "target": "comparison_table_gen_table_gen_default_output_dir", "relation": "calls", "context": "call", "confidence": "EXTRACTED", "source_file": "D:\\Git\\OpenJarvis-Windows-focused\\src\\openjarvis\\evals\\comparison\\table_gen.py", "source_location": "L394", "weight": 1.0}, {"source": "comparison_table_gen_main", "target": "comparison_table_gen_load_results", "relation": "calls", "context": "call", "confidence": "EXTRACTED", "source_file": "D:\\Git\\OpenJarvis-Windows-focused\\src\\openjarvis\\evals\\comparison\\table_gen.py", "source_location": "L398", "weight": 1.0}, {"source": "comparison_table_gen_rationale_1", "target": "d_git_openjarvis_windows_focused_src_openjarvis_evals_comparison_table_gen_py", "relation": "rationale_for", "confidence": "EXTRACTED", "source_file": "D:\\Git\\OpenJarvis-Windows-focused\\src\\openjarvis\\evals\\comparison\\table_gen.py", "source_location": "L1", "weight": 1.0}, {"source": "comparison_table_gen_rationale_34", "target": "comparison_table_gen_tablegenerror", "relation": "rationale_for", "confidence": "EXTRACTED", "source_file": "D:\\Git\\OpenJarvis-Windows-focused\\src\\openjarvis\\evals\\comparison\\table_gen.py", "source_location": "L34", "weight": 1.0}, {"source": "comparison_table_gen_rationale_38", "target": "comparison_table_gen_mixedcommiterror", "relation": "rationale_for", "confidence": "EXTRACTED", "source_file": "D:\\Git\\OpenJarvis-Windows-focused\\src\\openjarvis\\evals\\comparison\\table_gen.py", "source_location": "L38", "weight": 1.0}, {"source": "comparison_table_gen_rationale_42", "target": "comparison_table_gen_noresultserror", "relation": "rationale_for", "confidence": "EXTRACTED", "source_file": "D:\\Git\\OpenJarvis-Windows-focused\\src\\openjarvis\\evals\\comparison\\table_gen.py", "source_location": "L42", "weight": 1.0}, {"source": "comparison_table_gen_rationale_62", "target": "comparison_table_gen_resultsframe", "relation": "rationale_for", "confidence": "EXTRACTED", "source_file": "D:\\Git\\OpenJarvis-Windows-focused\\src\\openjarvis\\evals\\comparison\\table_gen.py", "source_location": "L62", "weight": 1.0}, {"source": "comparison_table_gen_rationale_69", "target": "comparison_table_gen_load_results", "relation": "rationale_for", "confidence": "EXTRACTED", "source_file": "D:\\Git\\OpenJarvis-Windows-focused\\src\\openjarvis\\evals\\comparison\\table_gen.py", "source_location": "L69", "weight": 1.0}, {"source": "comparison_table_gen_rationale_133", "target": "comparison_table_gen_format_cell", "relation": "rationale_for", "confidence": "EXTRACTED", "source_file": "D:\\Git\\OpenJarvis-Windows-focused\\src\\openjarvis\\evals\\comparison\\table_gen.py", "source_location": "L133", "weight": 1.0}, {"source": "comparison_table_gen_rationale_150", "target": "comparison_table_gen_render_booktabs", "relation": "rationale_for", "confidence": "EXTRACTED", "source_file": "D:\\Git\\OpenJarvis-Windows-focused\\src\\openjarvis\\evals\\comparison\\table_gen.py", "source_location": "L150", "weight": 1.0}, {"source": "comparison_table_gen_rationale_192", "target": "comparison_table_gen_build_t1", "relation": "rationale_for", "confidence": "EXTRACTED", "source_file": "D:\\Git\\OpenJarvis-Windows-focused\\src\\openjarvis\\evals\\comparison\\table_gen.py", "source_location": "L192", "weight": 1.0}, {"source": "comparison_table_gen_rationale_229", "target": "comparison_table_gen_build_t2", "relation": "rationale_for", "confidence": "EXTRACTED", "source_file": "D:\\Git\\OpenJarvis-Windows-focused\\src\\openjarvis\\evals\\comparison\\table_gen.py", "source_location": "L229", "weight": 1.0}, {"source": "comparison_table_gen_rationale_255", "target": "comparison_table_gen_build_t3", "relation": "rationale_for", "confidence": "EXTRACTED", "source_file": "D:\\Git\\OpenJarvis-Windows-focused\\src\\openjarvis\\evals\\comparison\\table_gen.py", "source_location": "L255", "weight": 1.0}, {"source": "comparison_table_gen_rationale_286", "target": "comparison_table_gen_build_t4", "relation": "rationale_for", "confidence": "EXTRACTED", "source_file": "D:\\Git\\OpenJarvis-Windows-focused\\src\\openjarvis\\evals\\comparison\\table_gen.py", "source_location": "L286", "weight": 1.0}, {"source": "comparison_table_gen_rationale_302", "target": "comparison_table_gen_build_t5", "relation": "rationale_for", "confidence": "EXTRACTED", "source_file": "D:\\Git\\OpenJarvis-Windows-focused\\src\\openjarvis\\evals\\comparison\\table_gen.py", "source_location": "L302", "weight": 1.0}, {"source": "comparison_table_gen_rationale_318", "target": "comparison_table_gen_build_t6", "relation": "rationale_for", "confidence": "EXTRACTED", "source_file": "D:\\Git\\OpenJarvis-Windows-focused\\src\\openjarvis\\evals\\comparison\\table_gen.py", "source_location": "L318", "weight": 1.0}, {"source": "comparison_table_gen_rationale_340", "target": "comparison_table_gen_build_t7", "relation": "rationale_for", "confidence": "EXTRACTED", "source_file": "D:\\Git\\OpenJarvis-Windows-focused\\src\\openjarvis\\evals\\comparison\\table_gen.py", "source_location": "L340", "weight": 1.0}, {"source": "comparison_table_gen_rationale_393", "target": "comparison_table_gen_main", "relation": "rationale_for", "confidence": "EXTRACTED", "source_file": "D:\\Git\\OpenJarvis-Windows-focused\\src\\openjarvis\\evals\\comparison\\table_gen.py", "source_location": "L393", "weight": 1.0}], "raw_calls": [{"caller_nid": "comparison_table_gen_load_results", "callee": "glob", "is_member_call": true, "source_file": "D:\\Git\\OpenJarvis-Windows-focused\\src\\openjarvis\\evals\\comparison\\table_gen.py", "source_location": "L70"}, {"caller_nid": "comparison_table_gen_load_results", "callee": "loads", "is_member_call": true, "source_file": "D:\\Git\\OpenJarvis-Windows-focused\\src\\openjarvis\\evals\\comparison\\table_gen.py", "source_location": "L76"}, {"caller_nid": "comparison_table_gen_load_results", "callee": "read_text", "is_member_call": true, "source_file": "D:\\Git\\OpenJarvis-Windows-focused\\src\\openjarvis\\evals\\comparison\\table_gen.py", "source_location": "L76"}, {"caller_nid": "comparison_table_gen_load_results", "callee": "model_validate", "is_member_call": true, "source_file": "D:\\Git\\OpenJarvis-Windows-focused\\src\\openjarvis\\evals\\comparison\\table_gen.py", "source_location": "L77"}, {"caller_nid": "comparison_table_gen_load_results", "callee": "warning", "is_member_call": true, "source_file": "D:\\Git\\OpenJarvis-Windows-focused\\src\\openjarvis\\evals\\comparison\\table_gen.py", "source_location": "L79"}, {"caller_nid": "comparison_table_gen_load_results", "callee": "items", "is_member_call": true, "source_file": "D:\\Git\\OpenJarvis-Windows-focused\\src\\openjarvis\\evals\\comparison\\table_gen.py", "source_location": "L82"}, {"caller_nid": "comparison_table_gen_load_results", "callee": "append", "is_member_call": true, "source_file": "D:\\Git\\OpenJarvis-Windows-focused\\src\\openjarvis\\evals\\comparison\\table_gen.py", "source_location": "L83"}, {"caller_nid": "comparison_table_gen_load_results", "callee": "is_empty", "is_member_call": true, "source_file": "D:\\Git\\OpenJarvis-Windows-focused\\src\\openjarvis\\evals\\comparison\\table_gen.py", "source_location": "L115"}, {"caller_nid": "comparison_table_gen_load_results", "callee": "agg", "is_member_call": true, "source_file": "D:\\Git\\OpenJarvis-Windows-focused\\src\\openjarvis\\evals\\comparison\\table_gen.py", "source_location": "L116"}, {"caller_nid": "comparison_table_gen_load_results", "callee": "group_by", "is_member_call": true, "source_file": "D:\\Git\\OpenJarvis-Windows-focused\\src\\openjarvis\\evals\\comparison\\table_gen.py", "source_location": "L116"}, {"caller_nid": "comparison_table_gen_load_results", "callee": "alias", "is_member_call": true, "source_file": "D:\\Git\\OpenJarvis-Windows-focused\\src\\openjarvis\\evals\\comparison\\table_gen.py", "source_location": "L117"}, {"caller_nid": "comparison_table_gen_load_results", "callee": "unique", "is_member_call": true, "source_file": "D:\\Git\\OpenJarvis-Windows-focused\\src\\openjarvis\\evals\\comparison\\table_gen.py", "source_location": "L117"}, {"caller_nid": "comparison_table_gen_load_results", "callee": "col", "is_member_call": true, "source_file": "D:\\Git\\OpenJarvis-Windows-focused\\src\\openjarvis\\evals\\comparison\\table_gen.py", "source_location": "L117"}, {"caller_nid": "comparison_table_gen_load_results", "callee": "iter_rows", "is_member_call": true, "source_file": "D:\\Git\\OpenJarvis-Windows-focused\\src\\openjarvis\\evals\\comparison\\table_gen.py", "source_location": "L119"}, {"caller_nid": "comparison_table_gen_render_booktabs", "callee": "append", "is_member_call": true, "source_file": "D:\\Git\\OpenJarvis-Windows-focused\\src\\openjarvis\\evals\\comparison\\table_gen.py", "source_location": "L160"}, {"caller_nid": "comparison_table_gen_render_booktabs", "callee": "append", "is_member_call": true, "source_file": "D:\\Git\\OpenJarvis-Windows-focused\\src\\openjarvis\\evals\\comparison\\table_gen.py", "source_location": "L161"}, {"caller_nid": "comparison_table_gen_render_booktabs", "callee": "append", "is_member_call": true, "source_file": "D:\\Git\\OpenJarvis-Windows-focused\\src\\openjarvis\\evals\\comparison\\table_gen.py", "source_location": "L162"}, {"caller_nid": "comparison_table_gen_render_booktabs", "callee": "join", "is_member_call": true, "source_file": "D:\\Git\\OpenJarvis-Windows-focused\\src\\openjarvis\\evals\\comparison\\table_gen.py", "source_location": "L162"}, {"caller_nid": "comparison_table_gen_render_booktabs", "callee": "append", "is_member_call": true, "source_file": "D:\\Git\\OpenJarvis-Windows-focused\\src\\openjarvis\\evals\\comparison\\table_gen.py", "source_location": "L163"}, {"caller_nid": "comparison_table_gen_render_booktabs", "callee": "iter_rows", "is_member_call": true, "source_file": "D:\\Git\\OpenJarvis-Windows-focused\\src\\openjarvis\\evals\\comparison\\table_gen.py", "source_location": "L164"}, {"caller_nid": "comparison_table_gen_render_booktabs", "callee": "append", "is_member_call": true, "source_file": "D:\\Git\\OpenJarvis-Windows-focused\\src\\openjarvis\\evals\\comparison\\table_gen.py", "source_location": "L167"}, {"caller_nid": "comparison_table_gen_render_booktabs", "callee": "append", "is_member_call": true, "source_file": "D:\\Git\\OpenJarvis-Windows-focused\\src\\openjarvis\\evals\\comparison\\table_gen.py", "source_location": "L168"}, {"caller_nid": "comparison_table_gen_render_booktabs", "callee": "join", "is_member_call": true, "source_file": "D:\\Git\\OpenJarvis-Windows-focused\\src\\openjarvis\\evals\\comparison\\table_gen.py", "source_location": "L168"}, {"caller_nid": "comparison_table_gen_render_booktabs", "callee": "append", "is_member_call": true, "source_file": "D:\\Git\\OpenJarvis-Windows-focused\\src\\openjarvis\\evals\\comparison\\table_gen.py", "source_location": "L169"}, {"caller_nid": "comparison_table_gen_render_booktabs", "callee": "append", "is_member_call": true, "source_file": "D:\\Git\\OpenJarvis-Windows-focused\\src\\openjarvis\\evals\\comparison\\table_gen.py", "source_location": "L170"}, {"caller_nid": "comparison_table_gen_render_booktabs", "callee": "join", "is_member_call": true, "source_file": "D:\\Git\\OpenJarvis-Windows-focused\\src\\openjarvis\\evals\\comparison\\table_gen.py", "source_location": "L171"}, {"caller_nid": "comparison_table_gen_build_t1", "callee": "col", "is_member_call": true, "source_file": "D:\\Git\\OpenJarvis-Windows-focused\\src\\openjarvis\\evals\\comparison\\table_gen.py", "source_location": "L198"}, {"caller_nid": "comparison_table_gen_build_t1", "callee": "pivot", "is_member_call": true, "source_file": "D:\\Git\\OpenJarvis-Windows-focused\\src\\openjarvis\\evals\\comparison\\table_gen.py", "source_location": "L200"}, {"caller_nid": "comparison_table_gen_build_t1", "callee": "agg", "is_member_call": true, "source_file": "D:\\Git\\OpenJarvis-Windows-focused\\src\\openjarvis\\evals\\comparison\\table_gen.py", "source_location": "L200"}, {"caller_nid": "comparison_table_gen_build_t1", "callee": "group_by", "is_member_call": true, "source_file": "D:\\Git\\OpenJarvis-Windows-focused\\src\\openjarvis\\evals\\comparison\\table_gen.py", "source_location": "L200"}, {"caller_nid": "comparison_table_gen_build_t1", "callee": "alias", "is_member_call": true, "source_file": "D:\\Git\\OpenJarvis-Windows-focused\\src\\openjarvis\\evals\\comparison\\table_gen.py", "source_location": "L201"}, {"caller_nid": "comparison_table_gen_build_t1", "callee": "mean", "is_member_call": true, "source_file": "D:\\Git\\OpenJarvis-Windows-focused\\src\\openjarvis\\evals\\comparison\\table_gen.py", "source_location": "L201"}, {"caller_nid": "comparison_table_gen_build_t1", "callee": "col", "is_member_call": true, "source_file": "D:\\Git\\OpenJarvis-Windows-focused\\src\\openjarvis\\evals\\comparison\\table_gen.py", "source_location": "L201"}, {"caller_nid": "comparison_table_gen_build_t1", "callee": "with_columns", "is_member_call": true, "source_file": "D:\\Git\\OpenJarvis-Windows-focused\\src\\openjarvis\\evals\\comparison\\table_gen.py", "source_location": "L206"}, {"caller_nid": "comparison_table_gen_build_t1", "callee": "alias", "is_member_call": true, "source_file": "D:\\Git\\OpenJarvis-Windows-focused\\src\\openjarvis\\evals\\comparison\\table_gen.py", "source_location": "L207"}, {"caller_nid": "comparison_table_gen_build_t1", "callee": "mean_horizontal", "is_member_call": true, "source_file": "D:\\Git\\OpenJarvis-Windows-focused\\src\\openjarvis\\evals\\comparison\\table_gen.py", "source_location": "L207"}, {"caller_nid": "comparison_table_gen_build_t1", "callee": "col", "is_member_call": true, "source_file": "D:\\Git\\OpenJarvis-Windows-focused\\src\\openjarvis\\evals\\comparison\\table_gen.py", "source_location": "L207"}, {"caller_nid": "comparison_table_gen_build_t2", "callee": "is_in", "is_member_call": true, "source_file": "D:\\Git\\OpenJarvis-Windows-focused\\src\\openjarvis\\evals\\comparison\\table_gen.py", "source_location": "L230"}, {"caller_nid": "comparison_table_gen_build_t2", "callee": "col", "is_member_call": true, "source_file": "D:\\Git\\OpenJarvis-Windows-focused\\src\\openjarvis\\evals\\comparison\\table_gen.py", "source_location": "L230"}, {"caller_nid": "comparison_table_gen_build_t2", "callee": "pivot", "is_member_call": true, "source_file": "D:\\Git\\OpenJarvis-Windows-focused\\src\\openjarvis\\evals\\comparison\\table_gen.py", "source_location": "L232"}, {"caller_nid": "comparison_table_gen_build_t2", "callee": "agg", "is_member_call": true, "source_file": "D:\\Git\\OpenJarvis-Windows-focused\\src\\openjarvis\\evals\\comparison\\table_gen.py", "source_location": "L232"}, {"caller_nid": "comparison_table_gen_build_t2", "callee": "group_by", "is_member_call": true, "source_file": "D:\\Git\\OpenJarvis-Windows-focused\\src\\openjarvis\\evals\\comparison\\table_gen.py", "source_location": "L232"}, {"caller_nid": "comparison_table_gen_build_t2", "callee": "alias", "is_member_call": true, "source_file": "D:\\Git\\OpenJarvis-Windows-focused\\src\\openjarvis\\evals\\comparison\\table_gen.py", "source_location": "L233"}, {"caller_nid": "comparison_table_gen_build_t2", "callee": "mean", "is_member_call": true, "source_file": "D:\\Git\\OpenJarvis-Windows-focused\\src\\openjarvis\\evals\\comparison\\table_gen.py", "source_location": "L233"}, {"caller_nid": "comparison_table_gen_build_t2", "callee": "col", "is_member_call": true, "source_file": "D:\\Git\\OpenJarvis-Windows-focused\\src\\openjarvis\\evals\\comparison\\table_gen.py", "source_location": "L233"}, {"caller_nid": "comparison_table_gen_build_t2", "callee": "rename", "is_member_call": true, "source_file": "D:\\Git\\OpenJarvis-Windows-focused\\src\\openjarvis\\evals\\comparison\\table_gen.py", "source_location": "L237"}, {"caller_nid": "comparison_table_gen_build_t2", "callee": "drop", "is_member_call": true, "source_file": "D:\\Git\\OpenJarvis-Windows-focused\\src\\openjarvis\\evals\\comparison\\table_gen.py", "source_location": "L238"}, {"caller_nid": "comparison_table_gen_build_t2", "callee": "with_columns", "is_member_call": true, "source_file": "D:\\Git\\OpenJarvis-Windows-focused\\src\\openjarvis\\evals\\comparison\\table_gen.py", "source_location": "L238"}, {"caller_nid": "comparison_table_gen_build_t2", "callee": "alias", "is_member_call": true, "source_file": "D:\\Git\\OpenJarvis-Windows-focused\\src\\openjarvis\\evals\\comparison\\table_gen.py", "source_location": "L239"}, {"caller_nid": "comparison_table_gen_build_t2", "callee": "col", "is_member_call": true, "source_file": "D:\\Git\\OpenJarvis-Windows-focused\\src\\openjarvis\\evals\\comparison\\table_gen.py", "source_location": "L239"}, {"caller_nid": "comparison_table_gen_build_t2", "callee": "col", "is_member_call": true, "source_file": "D:\\Git\\OpenJarvis-Windows-focused\\src\\openjarvis\\evals\\comparison\\table_gen.py", "source_location": "L239"}, {"caller_nid": "comparison_table_gen_build_t2", "callee": "select", "is_member_call": true, "source_file": "D:\\Git\\OpenJarvis-Windows-focused\\src\\openjarvis\\evals\\comparison\\table_gen.py", "source_location": "L244"}, {"caller_nid": "comparison_table_gen_build_t3", "callee": "col", "is_member_call": true, "source_file": "D:\\Git\\OpenJarvis-Windows-focused\\src\\openjarvis\\evals\\comparison\\table_gen.py", "source_location": "L256"}, {"caller_nid": "comparison_table_gen_build_t3", "callee": "is_in", "is_member_call": true, "source_file": "D:\\Git\\OpenJarvis-Windows-focused\\src\\openjarvis\\evals\\comparison\\table_gen.py", "source_location": "L258"}, {"caller_nid": "comparison_table_gen_build_t3", "callee": "col", "is_member_call": true, "source_file": "D:\\Git\\OpenJarvis-Windows-focused\\src\\openjarvis\\evals\\comparison\\table_gen.py", "source_location": "L258"}, {"caller_nid": "comparison_table_gen_build_t3", "callee": "pivot", "is_member_call": true, "source_file": "D:\\Git\\OpenJarvis-Windows-focused\\src\\openjarvis\\evals\\comparison\\table_gen.py", "source_location": "L270"}, {"caller_nid": "comparison_table_gen_build_t3", "callee": "agg", "is_member_call": true, "source_file": "D:\\Git\\OpenJarvis-Windows-focused\\src\\openjarvis\\evals\\comparison\\table_gen.py", "source_location": "L270"}, {"caller_nid": "comparison_table_gen_build_t3", "callee": "group_by", "is_member_call": true, "source_file": "D:\\Git\\OpenJarvis-Windows-focused\\src\\openjarvis\\evals\\comparison\\table_gen.py", "source_location": "L270"}, {"caller_nid": "comparison_table_gen_build_t3", "callee": "alias", "is_member_call": true, "source_file": "D:\\Git\\OpenJarvis-Windows-focused\\src\\openjarvis\\evals\\comparison\\table_gen.py", "source_location": "L271"}, {"caller_nid": "comparison_table_gen_build_t3", "callee": "mean", "is_member_call": true, "source_file": "D:\\Git\\OpenJarvis-Windows-focused\\src\\openjarvis\\evals\\comparison\\table_gen.py", "source_location": "L271"}, {"caller_nid": "comparison_table_gen_build_t3", "callee": "col", "is_member_call": true, "source_file": "D:\\Git\\OpenJarvis-Windows-focused\\src\\openjarvis\\evals\\comparison\\table_gen.py", "source_location": "L271"}, {"caller_nid": "comparison_table_gen_build_t3", "callee": "drop", "is_member_call": true, "source_file": "D:\\Git\\OpenJarvis-Windows-focused\\src\\openjarvis\\evals\\comparison\\table_gen.py", "source_location": "L274"}, {"caller_nid": "comparison_table_gen_build_t3", "callee": "with_columns", "is_member_call": true, "source_file": "D:\\Git\\OpenJarvis-Windows-focused\\src\\openjarvis\\evals\\comparison\\table_gen.py", "source_location": "L274"}, {"caller_nid": "comparison_table_gen_build_t3", "callee": "alias", "is_member_call": true, "source_file": "D:\\Git\\OpenJarvis-Windows-focused\\src\\openjarvis\\evals\\comparison\\table_gen.py", "source_location": "L275"}, {"caller_nid": "comparison_table_gen_build_t3", "callee": "col", "is_member_call": true, "source_file": "D:\\Git\\OpenJarvis-Windows-focused\\src\\openjarvis\\evals\\comparison\\table_gen.py", "source_location": "L275"}, {"caller_nid": "comparison_table_gen_build_t3", "callee": "col", "is_member_call": true, "source_file": "D:\\Git\\OpenJarvis-Windows-focused\\src\\openjarvis\\evals\\comparison\\table_gen.py", "source_location": "L275"}, {"caller_nid": "comparison_table_gen_build_t4", "callee": "col", "is_member_call": true, "source_file": "D:\\Git\\OpenJarvis-Windows-focused\\src\\openjarvis\\evals\\comparison\\table_gen.py", "source_location": "L287"}, {"caller_nid": "comparison_table_gen_build_t4", "callee": "pivot", "is_member_call": true, "source_file": "D:\\Git\\OpenJarvis-Windows-focused\\src\\openjarvis\\evals\\comparison\\table_gen.py", "source_location": "L289"}, {"caller_nid": "comparison_table_gen_build_t4", "callee": "agg", "is_member_call": true, "source_file": "D:\\Git\\OpenJarvis-Windows-focused\\src\\openjarvis\\evals\\comparison\\table_gen.py", "source_location": "L289"}, {"caller_nid": "comparison_table_gen_build_t4", "callee": "group_by", "is_member_call": true, "source_file": "D:\\Git\\OpenJarvis-Windows-focused\\src\\openjarvis\\evals\\comparison\\table_gen.py", "source_location": "L289"}, {"caller_nid": "comparison_table_gen_build_t4", "callee": "alias", "is_member_call": true, "source_file": "D:\\Git\\OpenJarvis-Windows-focused\\src\\openjarvis\\evals\\comparison\\table_gen.py", "source_location": "L290"}, {"caller_nid": "comparison_table_gen_build_t4", "callee": "mean", "is_member_call": true, "source_file": "D:\\Git\\OpenJarvis-Windows-focused\\src\\openjarvis\\evals\\comparison\\table_gen.py", "source_location": "L290"}, {"caller_nid": "comparison_table_gen_build_t4", "callee": "col", "is_member_call": true, "source_file": "D:\\Git\\OpenJarvis-Windows-focused\\src\\openjarvis\\evals\\comparison\\table_gen.py", "source_location": "L290"}, {"caller_nid": "comparison_table_gen_build_t6", "callee": "is_in", "is_member_call": true, "source_file": "D:\\Git\\OpenJarvis-Windows-focused\\src\\openjarvis\\evals\\comparison\\table_gen.py", "source_location": "L325"}, {"caller_nid": "comparison_table_gen_build_t6", "callee": "col", "is_member_call": true, "source_file": "D:\\Git\\OpenJarvis-Windows-focused\\src\\openjarvis\\evals\\comparison\\table_gen.py", "source_location": "L325"}, {"caller_nid": "comparison_table_gen_build_t6", "callee": "pivot", "is_member_call": true, "source_file": "D:\\Git\\OpenJarvis-Windows-focused\\src\\openjarvis\\evals\\comparison\\table_gen.py", "source_location": "L327"}, {"caller_nid": "comparison_table_gen_build_t6", "callee": "agg", "is_member_call": true, "source_file": "D:\\Git\\OpenJarvis-Windows-focused\\src\\openjarvis\\evals\\comparison\\table_gen.py", "source_location": "L327"}, {"caller_nid": "comparison_table_gen_build_t6", "callee": "group_by", "is_member_call": true, "source_file": "D:\\Git\\OpenJarvis-Windows-focused\\src\\openjarvis\\evals\\comparison\\table_gen.py", "source_location": "L327"}, {"caller_nid": "comparison_table_gen_build_t6", "callee": "alias", "is_member_call": true, "source_file": "D:\\Git\\OpenJarvis-Windows-focused\\src\\openjarvis\\evals\\comparison\\table_gen.py", "source_location": "L328"}, {"caller_nid": "comparison_table_gen_build_t6", "callee": "mean", "is_member_call": true, "source_file": "D:\\Git\\OpenJarvis-Windows-focused\\src\\openjarvis\\evals\\comparison\\table_gen.py", "source_location": "L328"}, {"caller_nid": "comparison_table_gen_build_t6", "callee": "col", "is_member_call": true, "source_file": "D:\\Git\\OpenJarvis-Windows-focused\\src\\openjarvis\\evals\\comparison\\table_gen.py", "source_location": "L328"}, {"caller_nid": "comparison_table_gen_build_t7", "callee": "col", "is_member_call": true, "source_file": "D:\\Git\\OpenJarvis-Windows-focused\\src\\openjarvis\\evals\\comparison\\table_gen.py", "source_location": "L346"}, {"caller_nid": "comparison_table_gen_build_t7", "callee": "pivot", "is_member_call": true, "source_file": "D:\\Git\\OpenJarvis-Windows-focused\\src\\openjarvis\\evals\\comparison\\table_gen.py", "source_location": "L348"}, {"caller_nid": "comparison_table_gen_build_t7", "callee": "agg", "is_member_call": true, "source_file": "D:\\Git\\OpenJarvis-Windows-focused\\src\\openjarvis\\evals\\comparison\\table_gen.py", "source_location": "L348"}, {"caller_nid": "comparison_table_gen_build_t7", "callee": "group_by", "is_member_call": true, "source_file": "D:\\Git\\OpenJarvis-Windows-focused\\src\\openjarvis\\evals\\comparison\\table_gen.py", "source_location": "L348"}, {"caller_nid": "comparison_table_gen_build_t7", "callee": "alias", "is_member_call": true, "source_file": "D:\\Git\\OpenJarvis-Windows-focused\\src\\openjarvis\\evals\\comparison\\table_gen.py", "source_location": "L349"}, {"caller_nid": "comparison_table_gen_build_t7", "callee": "mean", "is_member_call": true, "source_file": "D:\\Git\\OpenJarvis-Windows-focused\\src\\openjarvis\\evals\\comparison\\table_gen.py", "source_location": "L349"}, {"caller_nid": "comparison_table_gen_build_t7", "callee": "col", "is_member_call": true, "source_file": "D:\\Git\\OpenJarvis-Windows-focused\\src\\openjarvis\\evals\\comparison\\table_gen.py", "source_location": "L349"}, {"caller_nid": "comparison_table_gen_main", "callee": "mkdir", "is_member_call": true, "source_file": "D:\\Git\\OpenJarvis-Windows-focused\\src\\openjarvis\\evals\\comparison\\table_gen.py", "source_location": "L395"}, {"caller_nid": "comparison_table_gen_main", "callee": "mkdir", "is_member_call": true, "source_file": "D:\\Git\\OpenJarvis-Windows-focused\\src\\openjarvis\\evals\\comparison\\table_gen.py", "source_location": "L396"}, {"caller_nid": "comparison_table_gen_main", "callee": "echo", "is_member_call": true, "source_file": "D:\\Git\\OpenJarvis-Windows-focused\\src\\openjarvis\\evals\\comparison\\table_gen.py", "source_location": "L399"}, {"caller_nid": "comparison_table_gen_main", "callee": "is_empty", "is_member_call": true, "source_file": "D:\\Git\\OpenJarvis-Windows-focused\\src\\openjarvis\\evals\\comparison\\table_gen.py", "source_location": "L402"}, {"caller_nid": "comparison_table_gen_main", "callee": "ClickException", "is_member_call": true, "source_file": "D:\\Git\\OpenJarvis-Windows-focused\\src\\openjarvis\\evals\\comparison\\table_gen.py", "source_location": "L403"}, {"caller_nid": "comparison_table_gen_main", "callee": "strip", "is_member_call": true, "source_file": "D:\\Git\\OpenJarvis-Windows-focused\\src\\openjarvis\\evals\\comparison\\table_gen.py", "source_location": "L408"}, {"caller_nid": "comparison_table_gen_main", "callee": "split", "is_member_call": true, "source_file": "D:\\Git\\OpenJarvis-Windows-focused\\src\\openjarvis\\evals\\comparison\\table_gen.py", "source_location": "L408"}, {"caller_nid": "comparison_table_gen_main", "callee": "strip", "is_member_call": true, "source_file": "D:\\Git\\OpenJarvis-Windows-focused\\src\\openjarvis\\evals\\comparison\\table_gen.py", "source_location": "L408"}, {"caller_nid": "comparison_table_gen_main", "callee": "echo", "is_member_call": true, "source_file": "D:\\Git\\OpenJarvis-Windows-focused\\src\\openjarvis\\evals\\comparison\\table_gen.py", "source_location": "L411"}, {"caller_nid": "comparison_table_gen_main", "callee": "_TABLE_BUILDERS[name]", "is_member_call": false, "source_file": "D:\\Git\\OpenJarvis-Windows-focused\\src\\openjarvis\\evals\\comparison\\table_gen.py", "source_location": "L414"}, {"caller_nid": "comparison_table_gen_main", "callee": "echo", "is_member_call": true, "source_file": "D:\\Git\\OpenJarvis-Windows-focused\\src\\openjarvis\\evals\\comparison\\table_gen.py", "source_location": "L416"}, {"caller_nid": "comparison_table_gen_main", "callee": "write_text", "is_member_call": true, "source_file": "D:\\Git\\OpenJarvis-Windows-focused\\src\\openjarvis\\evals\\comparison\\table_gen.py", "source_location": "L418"}, {"caller_nid": "comparison_table_gen_main", "callee": "write_text", "is_member_call": true, "source_file": "D:\\Git\\OpenJarvis-Windows-focused\\src\\openjarvis\\evals\\comparison\\table_gen.py", "source_location": "L419"}, {"caller_nid": "comparison_table_gen_main", "callee": "echo", "is_member_call": true, "source_file": "D:\\Git\\OpenJarvis-Windows-focused\\src\\openjarvis\\evals\\comparison\\table_gen.py", "source_location": "L420"}]}